{
    "name": "Get Flagged emails",
    "flow": [
        {
            "id": 3,
            "module": "util:SetVariables",
            "version": 1,
            "parameters": {},
            "mapper": {
                "scope": "roundtrip",
                "variables": [
                    {
                        "name": "slack-channelid",
                        "value": "D19N44D36"
                    }
                ]
            },
            "metadata": {
                "designer": {
                    "x": 0,
                    "y": 0
                },
                "restore": {
                    "scope": {
                        "label": "One cycle"
                    },
                    "variables": {
                        "items": [
                            "undefined"
                        ]
                    }
                },
                "expect": [
                    {
                        "name": "variables",
                        "spec": [
                            {
                                "name": "name",
                                "type": "text",
                                "label": "Variable name",
                                "required": true
                            },
                            {
                                "name": "value",
                                "type": "any",
                                "label": "Variable value"
                            }
                        ],
                        "type": "array",
                        "label": "Variables"
                    },
                    {
                        "name": "scope",
                        "type": "select",
                        "label": "Variable lifetime",
                        "required": true,
                        "validate": {
                            "enum": [
                                "roundtrip",
                                "execution"
                            ]
                        }
                    }
                ],
                "interface": [
                    {
                        "name": "slack-channelid",
                        "type": "any",
                        "label": "slack-channelid"
                    }
                ]
            }
        },
        {
            "id": 8,
            "module": "microsoft-email:makeApiCall",
            "version": 2,
            "parameters": {
                "__IMTCONN__": 65921
            },
            "mapper": {
                "url": "/v1.0/me/messages?$filter=flag/flagStatus eq 'flagged'&$top=100",
                "method": "GET",
                "headers": [
                    {
                        "key": "Content-Type",
                        "value": "application/json"
                    }
                ]
            },
            "metadata": {
                "designer": {
                    "x": 300,
                    "y": 0
                },
                "restore": {
                    "qs": {
                        "mode": "chose",
                        "items": []
                    },
                    "method": {
                        "mode": "chose",
                        "label": "GET"
                    },
                    "headers": {
                        "mode": "chose",
                        "items": [
                            "undefined"
                        ]
                    },
                    "__IMTCONN__": {
                        "label": "My Microsoft 365 connection (Eric Minnick)"
                    }
                },
                "parameters": [
                    {
                        "name": "__IMTCONN__",
                        "type": "account",
                        "label": "Connection",
                        "required": true
                    }
                ],
                "expect": [
                    {
                        "name": "url",
                        "type": "text",
                        "label": "URL",
                        "required": true
                    },
                    {
                        "name": "method",
                        "type": "select",
                        "label": "Method",
                        "required": true,
                        "validate": {
                            "enum": [
                                "GET",
                                "POST",
                                "PUT",
                                "PATCH",
                                "DELETE"
                            ]
                        }
                    },
                    {
                        "name": "headers",
                        "spec": [
                            {
                                "name": "key",
                                "type": "text",
                                "label": "Key"
                            },
                            {
                                "name": "value",
                                "type": "text",
                                "label": "Value"
                            }
                        ],
                        "type": "array",
                        "label": "Headers"
                    },
                    {
                        "name": "qs",
                        "spec": [
                            {
                                "name": "key",
                                "type": "text",
                                "label": "Key"
                            },
                            {
                                "name": "value",
                                "type": "text",
                                "label": "Value"
                            }
                        ],
                        "type": "array",
                        "label": "Query String"
                    },
                    {
                        "name": "body",
                        "type": "any",
                        "label": "Body"
                    }
                ]
            }
        },
        {
            "id": 7,
            "module": "builtin:BasicFeeder",
            "version": 1,
            "parameters": {},
            "mapper": {
                "array": "{{8.body.value}}"
            },
            "metadata": {
                "designer": {
                    "x": 600,
                    "y": 0
                },
                "restore": {
                    "array": {
                        "mode": "edit"
                    }
                },
                "expect": [
                    {
                        "mode": "edit",
                        "name": "array",
                        "spec": [],
                        "type": "array",
                        "label": "Array"
                    }
                ]
            }
        },
        {
            "id": 2,
            "module": "util:TextAggregator",
            "version": 1,
            "parameters": {
                "feeder": 7,
                "rowSeparator": "\n"
            },
            "filter": {
                "name": "is flagged?",
                "conditions": [
                    [
                        {
                            "a": "{{7.flag.flagStatus}}",
                            "b": "notflagged",
                            "o": "text:notequal:ci"
                        }
                    ]
                ]
            },
            "mapper": {
                "value": "- <{{7.webLink}}|{{7.subject}}> [ <mailto:{{7.sender.emailAddress.address}}|{{7.sender.emailAddress.name}}> ]  "
            },
            "metadata": {
                "designer": {
                    "x": 900,
                    "y": 0,
                    "name": "JAM SANDWICH"
                },
                "restore": {
                    "feeder": {
                        "label": "Iterator [7]"
                    },
                    "rowSeparator": {
                        "label": "New row"
                    }
                },
                "parameters": [
                    {
                        "name": "rowSeparator",
                        "type": "select",
                        "label": "Row separator",
                        "validate": {
                            "enum": [
                                "\n",
                                "\t",
                                "other"
                            ]
                        }
                    }
                ],
                "expect": [
                    {
                        "name": "value",
                        "type": "text",
                        "label": "Text",
                        "multiline": true
                    }
                ],
                "advanced": true
            }
        },
        {
            "id": 13,
            "module": "json:TransformToJSON",
            "version": 1,
            "parameters": {
                "space": ""
            },
            "mapper": {
                "object": "**FLAGGED EMAIL**{{newline}}{{2.text}}"
            },
            "metadata": {
                "designer": {
                    "x": 1061,
                    "y": -303
                },
                "restore": {
                    "space": {
                        "label": ""
                    }
                },
                "parameters": [
                    {
                        "name": "space",
                        "type": "select",
                        "label": "Indentation",
                        "validate": {
                            "enum": [
                                "tab",
                                "2",
                                "4"
                            ]
                        }
                    }
                ],
                "expect": [
                    {
                        "name": "object",
                        "type": "any",
                        "label": "Object"
                    }
                ]
            }
        },
        {
            "id": 10,
            "module": "slack:MakeAPICall",
            "version": 3,
            "parameters": {
                "__IMTCONN__": 92572
            },
            "mapper": {
                "url": "chat.postMessage",
                "auth": "header",
                "body": "{ \"channel\": \"{{3.`slack-channelid`}}\",\"markdown_text\":{{13.json}} }",
                "method": "POST",
                "headers": [
                    {
                        "key": "Content-Type",
                        "value": "application/json; charset=utf-8"
                    }
                ],
                "slackdomain": "https://slack.com/api/"
            },
            "metadata": {
                "designer": {
                    "x": 1200,
                    "y": 0
                },
                "restore": {
                    "qs": {
                        "mode": "chose",
                        "items": []
                    },
                    "auth": {
                        "mode": "chose",
                        "label": "as a header"
                    },
                    "method": {
                        "mode": "chose",
                        "label": "POST"
                    },
                    "headers": {
                        "mode": "chose",
                        "items": [
                            "undefined"
                        ]
                    },
                    "__IMTCONN__": {
                        "label": "My Slack connection (minnick)"
                    },
                    "slackdomain": {
                        "mode": "chose",
                        "label": "https://slack.com/api/"
                    }
                },
                "parameters": [
                    {
                        "name": "__IMTCONN__",
                        "type": "account",
                        "label": "Connection",
                        "required": true
                    }
                ],
                "expect": [
                    {
                        "name": "url",
                        "type": "text",
                        "label": "URL",
                        "required": true
                    },
                    {
                        "name": "method",
                        "type": "select",
                        "label": "Method",
                        "required": true,
                        "validate": {
                            "enum": [
                                "GET",
                                "POST",
                                "PUT",
                                "PATCH",
                                "DELETE"
                            ]
                        }
                    },
                    {
                        "name": "headers",
                        "spec": [
                            {
                                "name": "key",
                                "type": "text",
                                "label": "Key"
                            },
                            {
                                "name": "value",
                                "type": "text",
                                "label": "Value"
                            }
                        ],
                        "type": "array",
                        "label": "Headers"
                    },
                    {
                        "name": "qs",
                        "spec": [
                            {
                                "name": "key",
                                "type": "text",
                                "label": "Key"
                            },
                            {
                                "name": "value",
                                "type": "text",
                                "label": "Value"
                            }
                        ],
                        "type": "array",
                        "label": "Query String"
                    },
                    {
                        "name": "body",
                        "type": "any",
                        "label": "Body"
                    },
                    {
                        "name": "slackdomain",
                        "type": "select",
                        "label": "Base URL",
                        "validate": {
                            "enum": [
                                "https://slack.com/api/",
                                "https://hooks.slack.com/"
                            ]
                        }
                    },
                    {
                        "name": "auth",
                        "type": "select",
                        "label": "Send access token",
                        "validate": {
                            "enum": [
                                "header",
                                "query"
                            ]
                        }
                    }
                ],
                "advanced": true
            }
        }
    ],
    "metadata": {
        "instant": false,
        "version": 1,
        "scenario": {
            "roundtrips": 1,
            "maxErrors": 3,
            "autoCommit": true,
            "autoCommitTriggerLast": true,
            "sequential": false,
            "confidential": false,
            "dataloss": false,
            "dlq": false
        },
        "designer": {
            "orphans": []
        },
        "zone": "app.workfrontfusion.com"
    }
}